proteingraphml/Analysis/Visualize.py
proteingraphml/Analysis/__init__.py
proteingraphml/Analysis/featureLabel.py
proteingraphml/DataAdapter/Adapter.py
proteingraphml/DataAdapter/__init__.py
proteingraphml/DataAdapter/biodata_helper.py
proteingraphml/GraphTools/__init__.py
proteingraphml/GraphTools/graph.py
proteingraphml/MLTools/Data/DataSet.py
proteingraphml/MLTools/Data/__init__.py
proteingraphml/MLTools/MetapathFeatures/__init__.py
proteingraphml/MLTools/MetapathFeatures/featureBuilder.py
proteingraphml/MLTools/MetapathFeatures/functions.py
proteingraphml/MLTools/MetapathFeatures/nodes.py
proteingraphml/MLTools/Models/__init__.py
proteingraphml/MLTools/Models/models.py
proteingraphml/MLTools/Procedures/XGBoost.py
proteingraphml/MLTools/Procedures/__init__.py
proteingraphml/MLTools/StaticFeatures/__init__.py
proteingraphml/MLTools/StaticFeatures/staticData.py
proteingraphml/MLTools/StaticFeatures/staticFiles.R
proteingraphml/MLTools/__init__.py
proteingraphml/__init__.py
proteingraphml-0.1.1.dist-info/LICENSE
proteingraphml-0.1.1.dist-info/WHEEL
proteingraphml-0.1.1.dist-info/METADATA
proteingraphml-0.1.1.dist-info/RECORD
