Metadata-Version: 2.1
Name: proteingraphml
Version: 0.1.1
Summary: Knowledge Graphs for Protein Science
Home-page: https://github.com/unmtransinfo/ProteinGraphML
License: BSD-2-Clause
Keywords: science,biology,machine learning,drug discovery
Author: UNM Translational Informatics
Author-email: datascience.software@salud.unm.edu
Requires-Python: >=3.8.1,<3.10
Classifier: Development Status :: 4 - Beta
Classifier: Environment :: Console
Classifier: Intended Audience :: Science/Research
Classifier: License :: OSI Approved :: BSD License
Classifier: Natural Language :: English
Classifier: Operating System :: MacOS :: MacOS X
Classifier: Operating System :: POSIX :: Linux
Classifier: Programming Language :: Python :: 3
Classifier: Programming Language :: Python :: 3.8
Classifier: Programming Language :: Python :: 3.9
Classifier: Topic :: Scientific/Engineering :: Bio-Informatics
Requires-Dist: PyYAML
Requires-Dist: XlsxWriter
Requires-Dist: colorama
Requires-Dist: matplotlib
Requires-Dist: mysqlclient
Requires-Dist: networkx
Requires-Dist: numpy
Requires-Dist: openpyxl
Requires-Dist: pandas
Requires-Dist: pony
Requires-Dist: pyreadr
Requires-Dist: raven[flask]
Requires-Dist: scikit-learn
Requires-Dist: xgboost
Requires-Dist: xlrd
Project-URL: Changelog, https://github.com/unmtransinfo/ProteinGraphML/releases
Project-URL: Documentation, https://github.com/unmtransinfo/ProteinGraphML
Project-URL: Repository, https://github.com/unmtransinfo/ProteinGraphML
